simsurvey/__init__.py
simsurvey/models.py
simsurvey/simulsurvey.py
simsurvey/simultarget.py
simsurvey/version.py
simsurvey/utils/__init__.py
simsurvey/utils/decorators.py
simsurvey/utils/model_tools.py
simsurvey/utils/mpladdon.py
simsurvey/utils/random.py
simsurvey/utils/skybins.py
simsurvey/utils/skyplot.py
simsurvey/utils/tools.py
simsurvey-0.7.3.dist-info/METADATA
simsurvey-0.7.3.dist-info/WHEEL
simsurvey-0.7.3.dist-info/top_level.txt
simsurvey-0.7.3.dist-info/RECORD
