Metadata-Version: 2.1
Name: simsurvey
Version: 0.7.3
Summary: simsurvey: Basic tools for simulating astronomical surveys
Home-page: https://github.com/ZwickyTransientFacility/simsurvey/
Author: Simsurvey Developers
Author-email: ufeindt@gmail.com, ana.sagues-carracedo@fysik.su.se
Maintainer: Ulrich Feindt, Ana Sagués Carracedo
Maintainer-email: ufeindt@gmail.com, ana.sagues-carracedo@fysik.su.se
License: BSD (3-clause)
Download-URL: https://github.com/ZwickyTransientFacility/tarball/
Platform: UNKNOWN
Classifier: Intended Audience :: Science/Research
Classifier: Programming Language :: Python :: 2.7
Classifier: Programming Language :: Python :: 3
Classifier: License :: OSI Approved :: BSD License
Classifier: Topic :: Scientific/Engineering :: Astronomy
Classifier: Operating System :: POSIX
Classifier: Operating System :: Unix
Classifier: Operating System :: MacOS
Requires-Dist: propobject (>=0.1.0)
Requires-Dist: astropy (>=1.2.1)
Requires-Dist: sncosmo (>=1.3.1)
Requires-Dist: sfdmap (>=0.1.0)
